lapsolverc.cp36-win32.pyd
lapsolver/__init__.py
lapsolver/data/dense/costs0.npz
lapsolver/data/dense/costs1.npz
lapsolver/data/dense/costs10.npz
lapsolver/data/dense/costs2.npz
lapsolver/data/dense/costs3.npz
lapsolver/data/dense/costs4.npz
lapsolver/data/dense/costs5.npz
lapsolver/data/dense/costs6.npz
lapsolver/data/dense/costs7.npz
lapsolver/data/dense/costs8.npz
lapsolver/data/dense/costs9.npz
lapsolver/etc/benchmark-dtype-int.png
lapsolver/etc/benchmark-dtype-numpy.float32.png
lapsolver/tests/__init__.py
lapsolver/tests/test_dense.py
lapsolver/tests/test_files.py
lapsolver-1.1.0.dist-info/METADATA
lapsolver-1.1.0.dist-info/RECORD
lapsolver-1.1.0.dist-info/WHEEL
lapsolver-1.1.0.dist-info/top_level.txt
