Metadata-Version: 2.1
Name: lapsolver
Version: 1.1.0
Summary: Fast linear assignment problem solvers
Home-page: https://github.com/cheind/py-lapsolver
Author: Christoph Heindl, Jack Valmadre
License: MIT
Keywords: hungarian munkres kuhn linear-sum-assignment bipartite-graph lap
Platform: UNKNOWN
Requires-Python: >=3
